tri/__init__.py
tri/admin.py
tri/apps.py
tri/forms.py
django_tristate-0.1.dist-info/LICENSE
django_tristate-0.1.dist-info/METADATA
django_tristate-0.1.dist-info/WHEEL
django_tristate-0.1.dist-info/top_level.txt
django_tristate-0.1.dist-info/RECORD
