Metadata-Version: 2.1
Name: django-tristate
Version: 0.1
Summary: A Django module providing a tri-state field
Home-page: https://github.com/chrysochos/django-tristate
Author: Ioannis Chrysochos
Author-email: ioannis.chrysochos@cytanet.com.cy
Classifier: Framework :: Django
Classifier: Programming Language :: Python :: 3
License-File: LICENSE
